Metadata-Version: 2.1
Name: epochis
Version: 1.1.1
Summary: A CLI to convert offsets from epoch to human readable dates
Home-page: https://github.com/robreeves/epochis
Author: Rob Reeves
Author-email: 
License: UNKNOWN
Platform: UNKNOWN
Classifier: Programming Language :: Python :: 3
Classifier: License :: OSI Approved :: MIT License
Classifier: Operating System :: OS Independent
Requires-Python: >=3.6
